kholodov_interpolate/__init__.py
kholodov_interpolate/interpolate.py
kholodov_interpolate-0.2.dist-info/METADATA
kholodov_interpolate-0.2.dist-info/WHEEL
kholodov_interpolate-0.2.dist-info/top_level.txt
kholodov_interpolate-0.2.dist-info/RECORD
