Metadata-Version: 2.1
Name: kholodov-interpolate
Version: 0.2
Summary: dummy projec
Home-page: UNKNOWN
Author-email: ksteklo@mail.ru
License: UNKNOWN
Platform: UNKNOWN
Requires-Dist: numpy
Requires-Dist: matplotlib
